mcp_servce/__init__.py
mcp_servce/main.py
mcp_servce/mcp_servce.py
mcp_servce-0.1.0.dist-info/METADATA
mcp_servce-0.1.0.dist-info/WHEEL
mcp_servce-0.1.0.dist-info/entry_points.txt
mcp_servce-0.1.0.dist-info/RECORD
